swiss_army_man/__init__.py
swiss_army_man/cache/__init__.py
swiss_army_man/cache/redis_cache.py
swiss_army_man/cache/with_cache.py
swiss_army_man/databases/__init__.py
swiss_army_man/databases/database_manager.py
swiss_army_man/django/__init__.py
swiss_army_man/django/boot.py
swiss_army_man/django/boot_jupyter.py
swiss_army_man/django/check_iterator.py
swiss_army_man/django/environment.py
swiss_army_man/django/query_to_df.py
swiss_army_man/ml/__init__.py
swiss_army_man/ml/analyze.py
swiss_army_man/ml/asset_preprocessor.py
swiss_army_man/ml/date_splitter.py
swiss_army_man/ml/gaussian_generator.py
swiss_army_man/ml/normalize.py
swiss_army_man/ml/zipf_generator.py
swiss_army_man/ruby/__init__.py
swiss_army_man/ruby/sidekiq.py
swiss_army_man/utils/__init__.py
swiss_army_man/utils/batcher.py
swiss_army_man/utils/date_utils.py
swiss_army_man/utils/file_utils.py
swiss_army_man/utils/grep.py
swiss_army_man/utils/is_iterable.py
swiss_army_man/utils/list_utils.py
swiss_army_man/utils/parse_datetime.py
swiss_army_man/utils/proj_root.py
swiss_army_man/utils/singleton.py
swiss_army_man/utils/string_methods.py
swiss_army_man/utils/type_checks.py
swiss_army_man-0.1.64.dist-info/METADATA
swiss_army_man-0.1.64.dist-info/WHEEL
swiss_army_man-0.1.64.dist-info/RECORD
